src/main.py
bskyshell-0.1.0.dist-info/METADATA
bskyshell-0.1.0.dist-info/WHEEL
bskyshell-0.1.0.dist-info/entry_points.txt
bskyshell-0.1.0.dist-info/RECORD
